django_elasticsearch_dsl_drf/__init__.py
django_elasticsearch_dsl_drf/analyzers.py
django_elasticsearch_dsl_drf/apps.py
django_elasticsearch_dsl_drf/compat.py
django_elasticsearch_dsl_drf/constants.py
django_elasticsearch_dsl_drf/elasticsearch_helpers.py
django_elasticsearch_dsl_drf/helpers.py
django_elasticsearch_dsl_drf/pagination.py
django_elasticsearch_dsl_drf/pip_helpers.py
django_elasticsearch_dsl_drf/serializers.py
django_elasticsearch_dsl_drf/utils.py
django_elasticsearch_dsl_drf/versions.py
django_elasticsearch_dsl_drf/viewsets.py
django_elasticsearch_dsl_drf/wrappers.py
django_elasticsearch_dsl_drf/fields/__init__.py
django_elasticsearch_dsl_drf/fields/common.py
django_elasticsearch_dsl_drf/fields/helpers.py
django_elasticsearch_dsl_drf/fields/nested_fields.py
django_elasticsearch_dsl_drf/filter_backends/__init__.py
django_elasticsearch_dsl_drf/filter_backends/faceted_search.py
django_elasticsearch_dsl_drf/filter_backends/highlight.py
django_elasticsearch_dsl_drf/filter_backends/mixins.py
django_elasticsearch_dsl_drf/filter_backends/source.py
django_elasticsearch_dsl_drf/filter_backends/aggregations/__init__.py
django_elasticsearch_dsl_drf/filter_backends/aggregations/bucket_aggregations.py
django_elasticsearch_dsl_drf/filter_backends/aggregations/metrics_aggregations.py
django_elasticsearch_dsl_drf/filter_backends/aggregations/pipeline_aggregations.py
django_elasticsearch_dsl_drf/filter_backends/filtering/__init__.py
django_elasticsearch_dsl_drf/filter_backends/filtering/common.py
django_elasticsearch_dsl_drf/filter_backends/filtering/geo_spatial.py
django_elasticsearch_dsl_drf/filter_backends/filtering/ids.py
django_elasticsearch_dsl_drf/filter_backends/filtering/nested.py
django_elasticsearch_dsl_drf/filter_backends/filtering/post_filter.py
django_elasticsearch_dsl_drf/filter_backends/ordering/__init__.py
django_elasticsearch_dsl_drf/filter_backends/ordering/common.py
django_elasticsearch_dsl_drf/filter_backends/ordering/geo_spatial.py
django_elasticsearch_dsl_drf-0.22.5.dist-info/LICENSE_GPL2.0.txt
django_elasticsearch_dsl_drf-0.22.5.dist-info/LICENSE_LGPL_2.1.txt
django_elasticsearch_dsl_drf-0.22.5.dist-info/METADATA
django_elasticsearch_dsl_drf-0.22.5.dist-info/WHEEL
django_elasticsearch_dsl_drf-0.22.5.dist-info/top_level.txt
django_elasticsearch_dsl_drf-0.22.5.dist-info/RECORD
